sentry_dingding/__init__.py
sentry_dingding/forms.py
sentry_dingding/plugin.py
wy_sentry_dingding-0.0.7.dist-info/LICENSE
wy_sentry_dingding-0.0.7.dist-info/METADATA
wy_sentry_dingding-0.0.7.dist-info/WHEEL
wy_sentry_dingding-0.0.7.dist-info/entry_points.txt
wy_sentry_dingding-0.0.7.dist-info/top_level.txt
wy_sentry_dingding-0.0.7.dist-info/RECORD
